rpath/__init__.py
rpath/main.py
rpath-0.1.4.dist-info/WHEEL
rpath-0.1.4.dist-info/METADATA
rpath-0.1.4.dist-info/RECORD
