Metadata-Version: 2.1
Name: rpath
Version: 0.1.4
Summary: R's path handling functions for Python
Author: Gwang-Jin Kim
Author-email: gwang.jin.kim.phd@gmail.com
Requires-Python: >=3.9,<4.0
Classifier: Programming Language :: Python :: 3
Classifier: Programming Language :: Python :: 3.10
Classifier: Programming Language :: Python :: 3.9
